{"automations":[{"url":"https://emergya7735.zendesk.com/api/v2/automations/360007893334.json","id":360007893334,"title":"Cerrar el ticket 4 días después de que el estado se haya definido como resuelto","active":true,"updated_at":"2018-02-26T10:39:52Z","created_at":"2018-02-26T10:39:52Z","actions":[{"field":"status","value":"closed"}],"conditions":{"all":[{"field":"status","operator":"is","value":"solved"},{"field":"SOLVED","operator":"greater_than","value":"96"}],"any":[]},"position":0,"raw_title":"Cerrar el ticket 4 días después de que el estado se haya definido como resuelto"},{"url":"https://emergya7735.zendesk.com/api/v2/automations/360007893354.json","id":360007893354,"title":"Notificación pendiente 24 horas","active":false,"updated_at":"2018-02-26T10:39:52Z","created_at":"2018-02-26T10:39:52Z","actions":[{"field":"notification_user","value":["requester_id","[{{ticket.account}}] Solicitud pendiente: {{ticket.title}}","Este es un mensaje para recordarle que su solicitud (n.° #{{ticket.id}}) está pendiente y espera sus comentarios.\n\n{{ticket.comments_formatted}}"]}],"conditions":{"all":[{"field":"PENDING","operator":"is","value":"24"},{"field":"ticket_is_public","operator":"is","value":"public"}],"any":[]},"position":9998,"raw_title":"Notificación pendiente 24 horas"},{"url":"https://emergya7735.zendesk.com/api/v2/automations/360007893374.json","id":360007893374,"title":"Notificación pendiente 5 días","active":false,"updated_at":"2018-02-26T10:39:52Z","created_at":"2018-02-26T10:39:52Z","actions":[{"field":"notification_user","value":["requester_id","[{{ticket.account}}] Solicitud pendiente: {{ticket.title}}","Este es un mensaje para recordarle que su solicitud (n.° #{{ticket.id}}) está pendiente desde hace 5 días y espera sus comentarios.\n\n{{ticket.comments_formatted}}"]}],"conditions":{"all":[{"field":"PENDING","operator":"is","value":"120"},{"field":"ticket_is_public","operator":"is","value":"public"}],"any":[]},"position":9999,"raw_title":"Notificación pendiente 5 días"}],"next_page":null,"previous_page":null,"count":3}